gamma_data/__init__.py
gamma_data/gamma_data.py
gamma_data/gamma_data_test.py
securereqnet/__init__.py
securereqnet/_nbdev.py
securereqnet/deployment.py
securereqnet/model_evaluation.py
securereqnet/models.py
securereqnet/pipeline.py
securereqnet/preprocessing.py
securereqnet/record_generator.py
securereqnet/shap_evals.py
securereqnet/utils.py
securereqnet/data/data.csv
securereqnet/data/word_embeddings-embed_size_100-epochs_100.csv
securereqnet/data/word_embeddings-embed_size_20-epochs_60.csv
securereqnet/pretrained_models/alpha.hdf5
securereqnet/pretrained_models/alpha/saved_model.pb
securereqnet/pretrained_models/alpha/1/saved_model.pb
securereqnet/pretrained_models/alpha/1/variables/variables.data-00000-of-00001
securereqnet/pretrained_models/alpha/1/variables/variables.index
securereqnet/pretrained_models/gamma/1608675009/saved_model.pb
securereqnet/pretrained_models/gamma/1608675009/assets/vocab_compute_and_apply_vocabulary_vocabulary
securereqnet/pretrained_models/gamma/1608675009/variables/variables.data-00000-of-00001
securereqnet/pretrained_models/gamma/1608675009/variables/variables.index
securereqnet-1.0.0.dist-info/LICENSE
securereqnet-1.0.0.dist-info/METADATA
securereqnet-1.0.0.dist-info/WHEEL
securereqnet-1.0.0.dist-info/entry_points.txt
securereqnet-1.0.0.dist-info/top_level.txt
securereqnet-1.0.0.dist-info/RECORD
