Metadata-Version: 2.1
Name: securereqnet
Version: 1.0.0
Summary: A description of your project
Home-page: https://github.com/rmclanton/securereqnet
Author: Nathan Cooper
Author-email: nacooper01@email.wm.edu
License: Apache Software License 2.0
Keywords: nbdev #Change this as desired
Platform: UNKNOWN
Classifier: Development Status :: 3 - Alpha
Classifier: Intended Audience :: Science/Research
Classifier: License :: OSI Approved :: Apache Software License
Classifier: Natural Language :: English
Classifier: Programming Language :: Python :: 3.6
Classifier: Programming Language :: Python :: 3.7
Classifier: Programming Language :: Python :: 3.8
Requires-Python: >=3.6
